MCRAMP-0.0.3.data/data/headers/Engine.hpp
MCRAMP-0.0.3.data/data/headers/MicroURNG.hpp
MCRAMP-0.0.3.data/data/headers/ReinterpretCtr.hpp
MCRAMP-0.0.3.data/data/headers/aes.h
MCRAMP-0.0.3.data/data/headers/array.h
MCRAMP-0.0.3.data/data/headers/ars.h
MCRAMP-0.0.3.data/data/headers/clangfeatures.h
MCRAMP-0.0.3.data/data/headers/compilerfeatures.h
MCRAMP-0.0.3.data/data/headers/consts.h
MCRAMP-0.0.3.data/data/headers/gccfeatures.h
MCRAMP-0.0.3.data/data/headers/geom.h
MCRAMP-0.0.3.data/data/headers/gsl_cbrng.h
MCRAMP-0.0.3.data/data/headers/gsl_microrng.h
MCRAMP-0.0.3.data/data/headers/iccfeatures.h
MCRAMP-0.0.3.data/data/headers/msvcfeatures.h
MCRAMP-0.0.3.data/data/headers/nvccfeatures.h
MCRAMP-0.0.3.data/data/headers/open64features.h
MCRAMP-0.0.3.data/data/headers/openclfeatures.h
MCRAMP-0.0.3.data/data/headers/pgccfeatures.h
MCRAMP-0.0.3.data/data/headers/philox.h
MCRAMP-0.0.3.data/data/headers/rand.h
MCRAMP-0.0.3.data/data/headers/ref.h
MCRAMP-0.0.3.data/data/headers/sse.h
MCRAMP-0.0.3.data/data/headers/sunprofeatures.h
MCRAMP-0.0.3.data/data/headers/threefry.h
MCRAMP-0.0.3.data/data/headers/u01fixedpt.h
MCRAMP-0.0.3.data/data/headers/xlcfeatures.h
mcramp/__init__.py
mcramp/mcramp.py
mcramp/visualisation.py
mcramp/geom/__init__.py
mcramp/geom/arm.cl
mcramp/geom/arm.py
mcramp/geom/banana.cl
mcramp/geom/banana.py
mcramp/geom/box.cl
mcramp/geom/box.py
mcramp/geom/cylinder_ext.cl
mcramp/geom/cylinder_ext.py
mcramp/geom/gprim.py
mcramp/geom/mesh.cl
mcramp/geom/mesh.py
mcramp/geom/plane.cl
mcramp/geom/plane.py
mcramp/geom/sphere.cl
mcramp/geom/sphere.py
mcramp/geom/sphere_int.cl
mcramp/geom/sphere_int.py
mcramp/include/consts.h
mcramp/include/geom.h
mcramp/include/rand.h
mcramp/include/ref.h
mcramp/include/Random123/MicroURNG.hpp
mcramp/include/Random123/ReinterpretCtr.hpp
mcramp/include/Random123/aes.h
mcramp/include/Random123/array.h
mcramp/include/Random123/ars.h
mcramp/include/Random123/gsl_microrng.h
mcramp/include/Random123/philox.h
MCRAMP-0.0.3.dist-info/LICENSE
MCRAMP-0.0.3.dist-info/METADATA
MCRAMP-0.0.3.dist-info/WHEEL
MCRAMP-0.0.3.dist-info/top_level.txt
MCRAMP-0.0.3.dist-info/RECORD
