Metadata-Version: 2.1
Name: MCRAMP
Version: 0.0.3
Summary: UNKNOWN
Home-page: UNKNOWN
Author: UNKNOWN
Author-email: UNKNOWN
License: UNKNOWN
Platform: UNKNOWN
Requires-Dist: pyopencl (==2019.1.2)
Requires-Dist: numpy
Requires-Dist: matplotlib
Requires-Dist: mcpl
